{
  "personality": {
    "title": "Personality",
    "id": "IPIP",
    "scaleValues": [1, 2, 3, 4, 5],
    "scale": [
      "Very Inaccurate",
      "Moderately Inaccurate",
      "Neither Accurate Nor Inaccurate",
      "Moderately Accurate",
      "Very Accurate"
    ],
    "dimensions": {
      "E": "Extraversion",
      "A": "Agreeableness",
      "C": "Conscientiousness",
      "S": "Emotional Stability",
      "O": "Openness"
    },
    "questions": [
      {
        "text": "I am the life of the party.",
        "dimension": "E"
      },
      {
        "text": "I feel little concern for others.",  
        "dimension": "A",
        "inverted": true
      }
    ]
  },
  "brainType": {
    "title": "Brain Type",
    "id": "QSEQ",
    "scaleValues": [0, 0, 1, 2],
    "scale": [
      "Very Inaccurate",
      "Moderately Inaccurate",
      "Moderately Accurate",
      "Very Accurate"
    ],
    "dimensions": {
      "E": "Empathising",
      "S": "Systematizing"
    },
    "questions": [
      {
        "text": "I can easily tell if someone else wants to enter a conversation.",
        "dimension": "E"
      },
      {
        "text": "I rarely read articles or web pages about new technology.",
        "dimension": "S",
        "inverted": true
      }
    ]
  },
  "gamerType": {
    "title": "Gamer Type",
    "id": "LOTR",
    "scaleValues": [1, 2, 3, 4, 5],
    "scale": [
      "Very Inaccurate",
      "Moderately Inaccurate",
      "Neither Accurate Nor Inaccurate",
      "Moderately Accurate",
      "Very Accurate"
    ],
    "dimensions": {
      "Co": "Competition",
      "Ch": "Challenge",
      "Fa": "Fantasy",
      "Ar": "Arousal",
      "St": "Story",
      "Es": "Escapism",
      "Lo": "Loss-Aversion",
      "Cu": "Customization",
      "Gr": "Grinding/Completion",
      "Au": "Autonomy/Exploration",
      "So": "Socializing",
      "Re": "Relationships",
      "Te": "Teamwork"
    },
    "categories": {
      "Ac": "Achievement",
      "Im": "Immersion",
      "Ar": "Arousal",
      "So": "Social"
    },
    "questions": [
      {
        "text": "I like to play to prove to my friends that I am the best",
        "dimension": "Co",
        "category": "Ac"
      },
      {
        "text": "Video game stories are not important to me",
        "dimension": "St",
        "category": "Im",
        "inverted": true
      },
      {
        "text": "I prefer games that allow me to play however I want",
        "dimension": "Au",
        "category": null
      }
    ]
  }
}